winmica/__init__.py
winmica-1.0.3.dist-info/licenses/LICENSE
winmica-1.0.3.dist-info/METADATA
winmica-1.0.3.dist-info/WHEEL
winmica-1.0.3.dist-info/top_level.txt
winmica-1.0.3.dist-info/RECORD
