Metadata-Version: 2.4
Name: winmica
Version: 1.0.3
Summary: Windows 11 Mica backdrop effects using official Windows API
Home-page: https://github.com/amnweb/winmica
Author: AmN
License: MIT
Project-URL: Bug Tracker, https://github.com/amnweb/winmica/issues
Classifier: Development Status :: 5 - Production/Stable
Classifier: Intended Audience :: Developers
Classifier: Programming Language :: Python :: 3
Classifier: Operating System :: Microsoft :: Windows :: Windows 11
Requires-Python: >=3.12
License-File: LICENSE
Dynamic: author
Dynamic: classifier
Dynamic: description
Dynamic: description-content-type
Dynamic: home-page
Dynamic: license
Dynamic: license-file
Dynamic: project-url
Dynamic: requires-python
Dynamic: summary
